aioafero/__init__.py
aioafero/anonomyize_data.py
aioafero/device.py
aioafero/errors.py
aioafero/types.py
aioafero/util.py
aioafero/v1/__init__.py
aioafero/v1/auth.py
aioafero/v1/v1_const.py
aioafero/v1/controllers/__init__.py
aioafero/v1/controllers/base.py
aioafero/v1/controllers/climate.py
aioafero/v1/controllers/device.py
aioafero/v1/controllers/event.py
aioafero/v1/controllers/exhaust_fan.py
aioafero/v1/controllers/fan.py
aioafero/v1/controllers/light.py
aioafero/v1/controllers/lock.py
aioafero/v1/controllers/portable_ac.py
aioafero/v1/controllers/security_system.py
aioafero/v1/controllers/security_system_keypad.py
aioafero/v1/controllers/security_system_sensor.py
aioafero/v1/controllers/switch.py
aioafero/v1/controllers/thermostat.py
aioafero/v1/controllers/valve.py
aioafero/v1/models/__init__.py
aioafero/v1/models/device.py
aioafero/v1/models/exhaust_fan.py
aioafero/v1/models/fan.py
aioafero/v1/models/features.py
aioafero/v1/models/hvac_mixin.py
aioafero/v1/models/light.py
aioafero/v1/models/lock.py
aioafero/v1/models/portable_ac.py
aioafero/v1/models/resource.py
aioafero/v1/models/security_system.py
aioafero/v1/models/security_system_keypad.py
aioafero/v1/models/security_system_sensor.py
aioafero/v1/models/sensor.py
aioafero/v1/models/standard_mixin.py
aioafero/v1/models/switch.py
aioafero/v1/models/thermostat.py
aioafero/v1/models/valve.py
aioafero-7.0.0.dist-info/METADATA
aioafero-7.0.0.dist-info/WHEEL
aioafero-7.0.0.dist-info/licenses/LICENSE.txt
aioafero-7.0.0.dist-info/RECORD
