Metadata-Version: 2.4
Name: aioafero
Version: 7.0.0
Summary: Talk to the Afero API asynchronously
Project-URL: Repository, https://github.com/Expl0dingBanana/aioafero
Project-URL: Changelog, https://github.com/Expl0dingBanana/aioafero/CHANGELOG.md
Author-email: Chris Dohmen <chris.dohmen11@gmail.com>
Maintainer: tpural
Maintainer-email: Chris Dohmen <chris.dohmen11@gmail.com>
License: The MIT License (MIT)
License-File: LICENSE.txt
Keywords: Afero,Afero IoT,Hubspace,Myko
Classifier: Development Status :: 4 - Beta
Classifier: Programming Language :: Python
Classifier: Programming Language :: Python :: 3.12
Classifier: Programming Language :: Python :: 3.13
Requires-Python: >=3.12
Requires-Dist: aiohttp
Requires-Dist: beautifulsoup4
Requires-Dist: securelogging>=1.0.1
Provides-Extra: cli
Requires-Dist: click; extra == 'cli'
Provides-Extra: test
Requires-Dist: aioresponses; extra == 'test'
Requires-Dist: anyio[trio]; extra == 'test'
Requires-Dist: pytest; extra == 'test'
Requires-Dist: pytest-aioresponses; extra == 'test'
Requires-Dist: pytest-asyncio; extra == 'test'
Requires-Dist: pytest-cov; extra == 'test'
Requires-Dist: pytest-mock; extra == 'test'
Requires-Dist: tox; extra == 'test'
